locked_dict/__init__.py
locked_dict/locked_dict.py
locked_dict-2023.10.22.dist-info/LICENSE
locked_dict-2023.10.22.dist-info/METADATA
locked_dict-2023.10.22.dist-info/WHEEL
locked_dict-2023.10.22.dist-info/top_level.txt
locked_dict-2023.10.22.dist-info/RECORD
